investorzilla/__init__.py
nskeyedunarchiver-1.5.1.dist-info/licenses/LICENSE
nskeyedunarchiver-1.5.1.dist-info/METADATA
nskeyedunarchiver-1.5.1.dist-info/WHEEL
nskeyedunarchiver-1.5.1.dist-info/top_level.txt
nskeyedunarchiver-1.5.1.dist-info/RECORD
