Metadata-Version: 2.4
Name: NSKeyedUnArchiver
Version: 1.5.1
Summary: Decodes Apple's NSKeyedArchiver that were archived into text or binary plist files and returns a usable Python dict
Author-email: Avi Alkalay <avi@unix.sh>
Project-URL: Homepage, https://github.com/avibrazil/NSKeyedUnArchiver
Project-URL: Source, https://github.com/avibrazil/NSKeyedUnArchiver
Project-URL: Issues, https://github.com/avibrazil/NSKeyedUnArchiver/issues/new/choose
Project-URL: Pypi, https://pypi.org/project/NSKeyedUnArchiver
Classifier: Development Status :: 5 - Production/Stable
Classifier: Intended Audience :: Developers
Classifier: Operating System :: OS Independent
Classifier: Programming Language :: Python
Classifier: Topic :: Software Development :: Libraries :: Python Modules
Classifier: Topic :: Text Processing :: Markup
Requires-Python: >=3.8
License-File: LICENSE
Dynamic: license-file
